bare/__init__.py
bare/_examples/customer.bin
bare/_examples/employee.bin
bare/_examples/people.bin
bare/_examples/terminated.bin
bare/barearray.py
bare/barestruct.py
bare/baretype.py
bare/data.py
bare/map.py
bare/misc.py
bare/number.py
bare/test_barearray.py
bare/test_barestruct.py
bare/test_data.py
bare/test_encoder.py
bare/test_map.py
bare/test_misc.py
bare/test_number.py
bare/test_union.py
bare/union.py
bare/util.py
pybare-1.2.5.dist-info/METADATA
pybare-1.2.5.dist-info/WHEEL
pybare-1.2.5.dist-info/entry_points.txt
pybare-1.2.5.dist-info/licenses/LICENSE
pybare-1.2.5.dist-info/RECORD
