Metadata-Version: 2.1
Name: pybare
Version: 1.2.5
Summary: A BARE Encoding Library and Data Validation Library for Python.
Author-Email: Noah Pederson <noah@packetlost.dev>
License: Copyright 2020 Noah Pederson
Classifier: Development Status :: 4 - Beta
Classifier: Intended Audience :: Developers
Classifier: Programming Language :: Python :: 3.10
Classifier: Programming Language :: Python :: 3.11
Classifier: Programming Language :: Python :: 3.12
Classifier: License :: OSI Approved :: MIT License
Classifier: Operating System :: OS Independent
Project-URL: Homepage, https://sr.ht/~chiefnoah/pybare/
Project-URL: Repository, https://git.sr.ht/~chiefnoah/pybare
Project-URL: Issues, https://todo.sr.ht/~chiefnoah/pybare
Project-URL: Changelog, https://git.sr.ht/~chiefnoah/pybare/tree/master/item/CHANGELOG.md
Requires-Python: >=3.10
